sellerdesk/.DS_Store
sellerdesk/__init__.py
sellerdesk/__main__.py
sellerdesk/apps/__init__.py
sellerdesk/cli/application.py
sellerdesk/cli/info/application.py
sellerdesk/cli/info/info.py
sellerdesk/core/settings.py
sellerdesk/packages/__init__.py
sellerdesk/services/__init__.py
sellerdesk-0.0.1.dist-info/METADATA
sellerdesk-0.0.1.dist-info/WHEEL
sellerdesk-0.0.1.dist-info/entry_points.txt
sellerdesk-0.0.1.dist-info/RECORD
